odoo/addons/base_product_mass_addition/README.rst
odoo/addons/base_product_mass_addition/__init__.py
odoo/addons/base_product_mass_addition/__manifest__.py
odoo/addons/base_product_mass_addition/i18n/base_product_mass_addition.pot
odoo/addons/base_product_mass_addition/i18n/es.po
odoo/addons/base_product_mass_addition/i18n/fr.po
odoo/addons/base_product_mass_addition/i18n/it.po
odoo/addons/base_product_mass_addition/models/__init__.py
odoo/addons/base_product_mass_addition/models/product_mass_addition.py
odoo/addons/base_product_mass_addition/models/product_product.py
odoo/addons/base_product_mass_addition/readme/CONTRIBUTORS.rst
odoo/addons/base_product_mass_addition/readme/DESCRIPTION.rst
odoo/addons/base_product_mass_addition/static/description/icon.png
odoo/addons/base_product_mass_addition/static/description/index.html
odoo/addons/base_product_mass_addition/tests/__init__.py
odoo/addons/base_product_mass_addition/tests/test_product_mass_addition.py
odoo/addons/base_product_mass_addition/tests/models/order.py
odoo/addons/base_product_mass_addition/views/product_view.xml
odoo_addon_base_product_mass_addition-16.0.1.0.0.6.dist-info/METADATA
odoo_addon_base_product_mass_addition-16.0.1.0.0.6.dist-info/WHEEL
odoo_addon_base_product_mass_addition-16.0.1.0.0.6.dist-info/top_level.txt
odoo_addon_base_product_mass_addition-16.0.1.0.0.6.dist-info/RECORD
