Metadata-Version: 2.1
Name: odoo-addon-base_product_mass_addition
Version: 16.0.1.0.0.6
Summary: Base Product Mass Addition
Home-page: https://github.com/OCA/product-attribute
Author: Akretion, GRAP, Odoo Community Association (OCA)
Author-email: support@odoo-community.org
License: AGPL-3
Classifier: Programming Language :: Python
Classifier: Framework :: Odoo
Classifier: Framework :: Odoo :: 16.0
Classifier: License :: OSI Approved :: GNU Affero General Public License v3
Requires-Python: >=3.10
Requires-Dist: odoo-addon-onchange-helper<16.1dev,>=16.0dev
Requires-Dist: odoo<16.1dev,>=16.0a
